{
  "WhitelistedUsers": {
    "default": {
      "hash": "defaultdata",
      "attackable": true,
      "level": 0,
      "tags": [
        {
          "text": "CAT V5 USER",
          "color": [
            255,
            255,
            0
          ]
        }
      ]
    },
    "554721871359377409": {
      "hash": "fdb381628d5a864d5e2295ddb3e2a670f591952b35e174e077397546b42efed659818f6d9734c0ecd3704459bf08d46a8b7132035382fd8c85a2e46ed0836181",
      "attackable": false,
      "level": "2",
      "tags": [
        {
          "text": "CAT V6",
          "color": [
            255,
            145,
            60
          ]
        }
      ]
    },
    "1200103047838318603": {
      "hash": "f2d6de501c8ecf850fa761534b18d186d623711f4aa2c507e92a46fcf39e0b397eb8ab7febfe1e050ffeb65318e1a74b8119713b04d9e6004dd7f6f10d5f5590",
      "attackable": false,
      "level": "2",
      "tags": [
        {
          "text": "CAT V6",
          "color": [
            255,
            145,
            60
          ]
        }
      ]
    },
    "1145068116007718952": {
      "hash": "1873e47f1caae23cc04d352bbd90530a84e381513357a3e27ecdfdbd745b15229053f7d628808963e128fbd0718c72dfbe120dc7d7e7f42cd5103207409018fb",
      "attackable": false,
      "level": "1",
      "tags": [
        {
          "text": "CAT V5 PREMIUM",
          "color": [
            255,
            145,
            60
          ]
        }
      ]
    },
    "1249706429909176321": {
      "hash": "9f0b72b45d584b25369a89ab1e57462172f4e4ec94801faddf779787c472488cb8d83a5200e0eae48f0656a65c13b1c9ca88e1a81878a9b5df29366941ba51a7",
      "attackable": false,
      "level": "1",
      "tags": [
        {
          "text": "CAT V5 PREMIUM",
          "color": [
            255,
            145,
            60
          ]
        }
      ]
    },
    "981187721647243274": {
      "hash": "f7dca0967b59f20fb0cd5bff1490d182432081f5d995c3653eeac08a7a8c07c650e42ff209c519717202f4069c016d778e21c09af469f5b1eb6a01788fe47d1d",
      "attackable": false,
      "level": "1",
      "tags": [
        {
          "text": "CAT V5 PREMIUM",
          "color": [
            255,
            145,
            60
          ]
        }
      ]
    },
    "644743648604454955": {
      "hash": "e421db688d7a2c266d83853528b8758f6cc09edab07bc9c864b96d97a34ee3bdcd93e788960dcc064c839fa830e76b029837eed88b3340af9a885b2f9352fc06",
      "attackable": false,
      "level": "2",
      "tags": [
        {
          "text": "CAT V6",
          "color": [
            255,
            145,
            60
          ]
        }
      ]
    },
    "1216584029621715013": {
      "hash": "ecd13d08065523576116581602c298984f8c827a05b3203e671c8854d10665e8718bc56ef892ba284c77d101e1373ff39ff7840985b51b017c6018bfbd52c3e4",
      "attackable": false,
      "level": "1",
      "tags": [
        {
          "text": "CAT V5 PREMIUM",
          "color": [
            255,
            145,
            60
          ]
        }
      ]
    },
    "1162625831282147431": {
      "hash": "30f1b81f72db124fe95d64d85db8b37be201f7cd3cfab1115b0e0042d0ec70bb0fb0c486a4d6ea4a02ee2cf02e0180d05c9a5fc10152b27d9b20d0744f323741",
      "attackable": false,
      "level": "1",
      "tags": [
        {
          "text": "CAT V5 PREMIUM",
          "color": [
            255,
            145,
            60
          ]
        }
      ]
    },
    "1218320917709590592": {
      "hash": "018b57f06404684092e54e3c43b08de722596f70c6d544397526d1dcb417064af0dd362f308cd8dd93acb7d971fb598d09e1f633cd6e37759c96b4a4de34e8a4",
      "attackable": false,
      "level": "2",
      "tags": [
        {
          "text": "sigma",
          "color": [
            255,
            180,
            60
          ]
        }
      ]
    }
  },
  "BlacklistedUsers": {},
  "Announcement": {
    "text": "kys",
    "expiretime": 1619510977,
    "targets": "all"
  }
}